Metadata-Version: 2.1
Name: import-r
Version: 0.1
Summary: Enables importing R packages and files (like python modules) in python syntax via rpy2.
Home-page: https://github.com/mwort/python-r-import
Author: Michel Wortmann
Author-email: michel.wortmann@ouce.ox.ac.uk
License: MIT
Platform: UNKNOWN
Classifier: Development Status :: 3 - Alpha
Classifier: Programming Language :: Python :: 3
Classifier: License :: OSI Approved :: MIT License
Classifier: Topic :: Scientific/Engineering
Requires-Python: >=3.5
Provides-Extra: rcli
Provides-Extra: test
License-File: LICENSE
